account_utils/__init__.py
account_utils/activity.py
account_utils/scopes.py
account_utils-0.0.3.dist-info/METADATA
account_utils-0.0.3.dist-info/WHEEL
account_utils-0.0.3.dist-info/top_level.txt
account_utils-0.0.3.dist-info/RECORD
