Metadata-Version: 2.1
Name: account-utils
Version: 0.0.3
Summary: A small package supports account functions
Home-page: https://github.com/F4-Plus-DUT/BE-orphanage-management
Author: VietDev
Author-email: vietdev@gmail.com
Project-URL: Bug Tracker, https://github.com/F4-Plus-DUT/BE-orphanage-management/issues
Classifier: Programming Language :: Python :: 3
Classifier: License :: OSI Approved :: MIT License
Classifier: Operating System :: OS Independent
Requires-Python: >=3.6
